{
  "id": "圍",
  "kanjialiveData": null,
  "jishoData": {
    "query": "圍",
    "found": true,
    "strokeCount": 13,
    "meaning": "enclose, surround, encircle, preserve, store, keep",
    "kunyomi": [
      "かこ.む",
      "かこ.う",
      "かこ.い"
    ],
    "onyomi": [
      "イ"
    ],
    "onyomiExamples": [],
    "kunyomiExamples": [],
    "radical": {
      "symbol": "囗",
      "meaning": "enclosure"
    },
    "parts": [
      "口",
      "囗",
      "韋"
    ],
    "strokeOrderDiagramUri": "http://classic.jisho.org/static/images/stroke_diagrams/22285_frames.png",
    "strokeOrderSvgUri": "https://d1w6u4xc3l95km.cloudfront.net/kanji-2015-03/0570d.svg",
    "strokeOrderGifUri": "https://raw.githubusercontent.com/mistval/kanji_images/master/gifs/570d.gif",
    "uri": "https://jisho.org/search/%E5%9C%8D%23kanji"
  },
  "hanviet": [
    "vè"
  ],
  "vietnameseMeaning": [
    "① Vây quanh, như vi thành 圍城 vây thành. ② Vây bắt, chăng lưới bắt các giống thú gọi là đả vi 打圍. ③ Thước tròn, dùng để đo các đồ tròn gọi là vi. Hoặc cho 5 tấc là một vi hoặc cho một chét là một vi. ① Vây, bao vây, vây bắt: 圍而不打 Vây mà không đánh; 打圍 Giăng lưới bắt thú; ② Xung quanh: 周圍都是山Xung quanh đều là núi; ③ Khoanh tròn, cuộn, quàng: 床圍子 Vải khoanh giường; 圍紅領巾 Quàng khăn quàng đỏ; ④ Ôm: 樹大十圍 Cây to đến 10 ôm."
  ]
}