{
  "id": "尉",
  "kanjialiveData": null,
  "jishoData": {
    "query": "尉",
    "found": true,
    "taughtIn": "junior high",
    "jlptLevel": "N1",
    "newspaperFrequencyRank": "2007",
    "strokeCount": 11,
    "meaning": "military officer, jailer, old man, rank",
    "kunyomi": [],
    "onyomi": [
      "イ",
      "ジョウ"
    ],
    "onyomiExamples": [
      {
        "example": "尉官",
        "reading": "イカン",
        "meaning": "officer below the rank of major, company officer"
      },
      {
        "example": "中尉",
        "reading": "チュウイ",
        "meaning": "first lieutenant, lieutenant junior grade"
      },
      {
        "example": "少尉",
        "reading": "ショウイ",
        "meaning": "second lieutenant, sublieutenant, ensign"
      },
      {
        "example": "尉",
        "reading": "ジョウ",
        "meaning": "inspector (third highest of the four administrative ranks of the ritsuryō system), old man, white ash (of charcoal)"
      },
      {
        "example": "尉鶲",
        "reading": "ジョウビタキ",
        "meaning": "Daurian redstart (Phoenicurus auroreus)"
      },
      {
        "example": "黒式尉",
        "reading": "コクシキジョウ",
        "meaning": "noh mask used for old man roles (usu. black)"
      }
    ],
    "kunyomiExamples": [],
    "radical": {
      "symbol": "寸",
      "meaning": "thumb, inch"
    },
    "parts": [
      "二",
      "寸",
      "小",
      "尸",
      "示"
    ],
    "strokeOrderDiagramUri": "http://classic.jisho.org/static/images/stroke_diagrams/23561_frames.png",
    "strokeOrderSvgUri": "https://d1w6u4xc3l95km.cloudfront.net/kanji-2015-03/05c09.svg",
    "strokeOrderGifUri": "https://raw.githubusercontent.com/mistval/kanji_images/master/gifs/5c09.gif",
    "uri": "https://jisho.org/search/%E5%B0%89%23kanji"
  },
  "hanviet": [
    "úy"
  ],
  "vietnameseMeaning": [
    "(15n) uý uất ① Quan uý, các quan coi ngục và bắt trộm giặc đời xưa đều gọi là uý, như đình uý 廷尉, huyện uý 縣尉 đều lấy cái nghĩa trừ kẻ gian cho dân yên cả. ② Quân uý, quan binh đời Tần đều gọi là uý, như thái uý 太尉, đô uý 都尉, hiệu uý 校尉, v.v. ③ Một âm là uất. Uất trì 尉遲 họ Uất-trì. ① Yên. Như hân uý 欣慰 yên vui, uý lạo 慰勞 yên ủi. ① (Quân hàm cấp) uý: 大尉 Đại úy; 中尉 Trung úy; 少尉 Thiếu úy; ② (cũ) Quan úy (quan coi ngục và bắt trộm thời xưa): 廷尉 Đình úy; 縣尉 Huyện úy; ③ (cũ) Quân úy (quan binh đời Tần, Hán ở Trung Quốc thời xưa): 太尉 Thái úy; 都尉 Đô úy; 校尉 Hiệu úy; ④ (Họ) Úy. Xem 尉 . 【尉遲】Uất Trì (Họ) Uất Trì. Xem 尉 ."
  ],
  "jlpt": "1",
  "frequency": "2007",
  "grade": "8"
}