{
  "id": "惹",
  "kanjialiveData": null,
  "jishoData": {
    "query": "惹",
    "found": true,
    "strokeCount": 12,
    "meaning": "attract, captivate",
    "kunyomi": [
      "ひ.く"
    ],
    "onyomi": [
      "ジャク",
      "ジャ"
    ],
    "onyomiExamples": [
      {
        "example": "惹起",
        "reading": "ジャッキ",
        "meaning": "bringing about, cause, provocation"
      },
      {
        "example": "惹句",
        "reading": "ジャック",
        "meaning": "catchphrase (esp. in advertising)"
      }
    ],
    "kunyomiExamples": [
      {
        "example": "惹く",
        "reading": "ひく",
        "meaning": "to draw (attention, sympathy, etc.), to attract (e.g. interest)"
      }
    ],
    "radical": {
      "symbol": "心",
      "forms": [
        "忄",
        "⺗"
      ],
      "meaning": "heart"
    },
    "parts": [
      "ノ",
      "一",
      "口",
      "心",
      "艾"
    ],
    "strokeOrderDiagramUri": "http://classic.jisho.org/static/images/stroke_diagrams/24825_frames.png",
    "strokeOrderSvgUri": "https://d1w6u4xc3l95km.cloudfront.net/kanji-2015-03/060f9.svg",
    "strokeOrderGifUri": "https://raw.githubusercontent.com/mistval/kanji_images/master/gifs/60f9.gif",
    "uri": "https://jisho.org/search/%E6%83%B9%23kanji"
  },
  "vietnameseMeaning": [
    "① Rước lấy, như nhạ hận 惹恨 rước lấy sự ân hận. ② Tục gọi sự khêu lên gợi lên một sự gì là nhạ. ③ Xảy ra. ④ Dắt dẫn. ① Gây ra, chuốc lấy, rước lấy: 不要惹事 Không nên gây chuyện; 惹恨 Rước lấy điều ân hận; ② Khêu lên, gợi lên; ③ Xảy ra; ④ Khiến cho: 惹人注意 Khiến mọi người chú ý; ⑤ Trêu, trêu ghẹo, châm chọc: 這個孩子脾氣大，別惹他 Thằng bé này khó tính lắm, đừng trêu nó ⑥ Dắt dẫn."
  ],
  "hanviet": [
    "nhạ"
  ],
  "grade": "9"
}