{
  "id": "樂",
  "kanjialiveData": null,
  "jishoData": {
    "query": "樂",
    "found": true,
    "strokeCount": 15,
    "meaning": "music, comfort",
    "kunyomi": [
      "たの.しい",
      "たの.しむ",
      "この.む"
    ],
    "onyomi": [
      "ガク",
      "ラク",
      "ゴウ"
    ],
    "onyomiExamples": [
      {
        "example": "楽員",
        "reading": "ガクイン",
        "meaning": "bandsman"
      },
      {
        "example": "楽園",
        "reading": "ラクエン",
        "meaning": "paradise, Eden"
      },
      {
        "example": "千秋楽",
        "reading": "センシュウラク",
        "meaning": "final day of a performance, closing date, final show, final day of a tournament"
      }
    ],
    "kunyomiExamples": [],
    "radical": {
      "symbol": "木",
      "meaning": "tree"
    },
    "parts": [
      "幺",
      "木",
      "白"
    ],
    "strokeOrderDiagramUri": "http://classic.jisho.org/static/images/stroke_diagrams/27138_frames.png",
    "strokeOrderSvgUri": "https://d1w6u4xc3l95km.cloudfront.net/kanji-2015-03/06a02.svg",
    "strokeOrderGifUri": "https://raw.githubusercontent.com/mistval/kanji_images/master/gifs/6a02.gif",
    "uri": "https://jisho.org/search/%E6%A8%82%23kanji"
  },
  "hanviet": [
    "lạc"
  ],
  "vietnameseMeaning": [
    "① Nhạc, ngũ âm bát thanh đều gọi là âm nhạc cả. ② Một âm là lạc. Vui, thích. ③ Lại một âm là nhạo. Yêu thích, như trí giả nhạo thuỷ 知者樂水 kẻ trí thích nước. ① Vui, vui mừng, mừng: 樂事 Chuyện vui; 心裡樂得像開了花 Mừng như nở hoa trong bụng; 樂莫樂兮生相知 Vui thì không gì vui bằng sống mà được biết nhau; ② Thích thú: 樂此不疲 Thích thú quên cả mệt mỏi; ③ (khn) Cười: 他說了個笑話，把大家逗樂了 Anh ấy nói câu chuyện đùa, làm cho mọi người đều bật cười; ④ (Họ) Lạc. Xem 樂 , . (văn) Yêu thích: 智者樂水 Người trí thì thích nước. Xem 樂 , . ① Âm nhạc: 奏樂 Cử nhạc, tấu nhạc, chơi nhạc; ② (Họ) Nhạc. Xem 樂 , ."
  ],
  "grade": "10"
}