{
  "id": "膰",
  "kanjialiveData": null,
  "jishoData": {
    "query": "膰",
    "found": true,
    "strokeCount": 16,
    "meaning": "offerings to gods",
    "kunyomi": [
      "ひもごり",
      "ひもろぎ"
    ],
    "onyomi": [
      "ハン"
    ],
    "onyomiExamples": [],
    "kunyomiExamples": [
      {
        "example": "胙",
        "reading": "ひもろぎ",
        "meaning": "offerings of food (to the gods)"
      }
    ],
    "radical": {
      "symbol": "肉",
      "forms": [
        "⺼"
      ],
      "meaning": "meat"
    },
    "parts": [
      "月",
      "田",
      "米",
      "釆"
    ],
    "strokeOrderDiagramUri": "http://classic.jisho.org/static/images/stroke_diagrams/33200_frames.png",
    "strokeOrderSvgUri": "https://d1w6u4xc3l95km.cloudfront.net/kanji-2015-03/081b0.svg",
    "strokeOrderGifUri": "https://raw.githubusercontent.com/mistval/kanji_images/master/gifs/81b0.gif",
    "uri": "https://jisho.org/search/%E8%86%B0%23kanji"
  },
  "vietnameseMeaning": [
    "① Thịt phần tế, thịt luộc chín đem tế rồi chia phần gọi là phiền nhục 膰肉. Ta quen đọc là chữ phần. (cũ) Thịt luộc chín dùng để cúng tế, phần thịt tế."
  ],
  "hanviet": [
    "phiền",
    "phần"
  ]
}