{
  "id": "阿",
  "kanjialiveData": null,
  "jishoData": {
    "query": "阿",
    "found": true,
    "jlptLevel": "N1",
    "newspaperFrequencyRank": "1126",
    "strokeCount": 8,
    "meaning": "Africa, flatter, fawn upon, corner, nook, recess",
    "kunyomi": [
      "おもね.る",
      "くま"
    ],
    "onyomi": [
      "ア",
      "オ"
    ],
    "onyomiExamples": [
      {
        "example": "阿",
        "reading": "ア",
        "meaning": "first Sanskrit alphabet letter, Africa, Awa (old province of Japan), prefixed to names to show intimacy"
      },
      {
        "example": "【アホ】",
        "reading": "fool, idiot, simpleton",
        "meaning": ""
      },
      {
        "example": "南ア",
        "reading": "ナンア",
        "meaning": "South Africa"
      },
      {
        "example": "阿蘭陀",
        "reading": "オランダ",
        "meaning": "Netherlands, Holland"
      },
      {
        "example": "お亀",
        "reading": "オカメ",
        "meaning": "homely woman (esp. one with a small low nose, high flat forehead, and bulging cheeks), plain woman, soba in soup with slices of boiled fish paste, shiitake mushrooms, greens, seaweed, etc."
      },
      {
        "example": "加加阿",
        "reading": "カカオ",
        "meaning": "cacao tree (Theobroma cacao), cocoa tree"
      }
    ],
    "kunyomiExamples": [
      {
        "example": "阿る",
        "reading": "おもねる",
        "meaning": "to flatter, to play up (to), to curry favor (with), to fawn (on), to cater (to)"
      },
      {
        "example": "隈",
        "reading": "くま",
        "meaning": "corner, nook, recess, shade, shadow, dark area, dark circles (under the eyes), dark rings, bend (in a road, river, etc.), shading, gradation, kumadori, style of kabuki makeup used for violent roles"
      }
    ],
    "radical": {
      "symbol": "阜",
      "forms": [
        "阝"
      ],
      "meaning": "mound, dam (阝 left)"
    },
    "parts": [
      "一",
      "亅",
      "口",
      "阡"
    ],
    "strokeOrderDiagramUri": "http://classic.jisho.org/static/images/stroke_diagrams/38463_frames.png",
    "strokeOrderSvgUri": "https://d1w6u4xc3l95km.cloudfront.net/kanji-2015-03/0963f.svg",
    "strokeOrderGifUri": "https://raw.githubusercontent.com/mistval/kanji_images/master/gifs/963f.gif",
    "uri": "https://jisho.org/search/%E9%98%BF%23kanji"
  },
  "vietnameseMeaning": [
    "a, á a ① Cái đống lớn, cái gò to. ② Tựa. Ngày xưa dùng đặt tên quan lấy ý rằng cái người ấy có thể nương tựa được. Như a hành 阿衡, a bảo 阿保, v.v. ③ A dua. Như a tư sở hiếu 阿私所好 dua theo cái mình thích riêng. ④ Bờ bên nước. ⑤ Cái cột. ⑥ Dài mà dẹp. ⑦ Một âm là á. Dùng làm lời giáo đầu. Như ta nói a, à. (đph) ① Tiếng đặt ở trước câu hoặc trước tên gọi: 阿哥 Anh ơi!; 阿爹 Cha ơi!; 阿婆 bà ơi!; 阿王 Em Vương này!.【阿誰】a thùy (văn) a. Ai? (có thể làm chủ ngữ, vị ngữ hoặc tân ngữ): 桃李小園空，阿誰猶笑語？ Mảnh vườn con đào lí trống trơn, còn ai cười nói? (Tổ Khả: Tiểu trùng sơn); 敦作色曰：小人阿 誰？ Đôn đổi sắc mặt hỏi: Tiểu nhân là ai? (Tấn thư: Vương Đôn truyện); 家中有阿誰？ Trong nhà có ai? (Nhạc phủ thi tập); b. Thứ nào, cái nào, ai?: 向者之論，阿誰爲失？ Lời nói (của hai người) lúc nãy, ai là sai? (Tam quốc chí); ② Dùng trong từ phiên âm một số tên nước ngoài: 阿爾巴尼亞 An-ba-ni, 阿 爾及利亞 An-giê-ri. Xem 阿 . ① Đón ý hùa theo, a dua, thiên về một bên: 阿其所好 Hùa theo ý muốn của người khác; ② (văn) Tựa, dựa vào; ③ (văn) Bờ sông, bờ nước, ven sông; ④ (văn) Góc, cạnh; ⑤ (văn) Cây cột, cột trụ; ⑥ (văn) Gò lớn; ⑦ (văn) Thon và đẹp; ⑧ (văn) Tiết ra, tháo ra (cứt, đái...). Xem 阿 ."
  ],
  "jlpt": "1",
  "frequency": "1126",
  "grade": "9"
}