{
  "id": "需",
  "kanjialiveData": null,
  "jishoData": {
    "query": "需",
    "found": true,
    "taughtIn": "junior high",
    "jlptLevel": "N1",
    "newspaperFrequencyRank": "935",
    "strokeCount": 14,
    "meaning": "demand, request, need",
    "kunyomi": [],
    "onyomi": [
      "ジュ"
    ],
    "onyomiExamples": [
      {
        "example": "需要",
        "reading": "ジュヨウ",
        "meaning": "demand, request"
      },
      {
        "example": "需給",
        "reading": "ジュキュウ",
        "meaning": "supply and demand"
      },
      {
        "example": "外需",
        "reading": "ガイジュ",
        "meaning": "foreign demand"
      },
      {
        "example": "内需",
        "reading": "ナイジュ",
        "meaning": "domestic demand"
      }
    ],
    "kunyomiExamples": [],
    "radical": {
      "symbol": "雨",
      "meaning": "rain"
    },
    "parts": [
      "而",
      "雨"
    ],
    "strokeOrderDiagramUri": "http://classic.jisho.org/static/images/stroke_diagrams/38656_frames.png",
    "strokeOrderSvgUri": "https://d1w6u4xc3l95km.cloudfront.net/kanji-2015-03/09700.svg",
    "strokeOrderGifUri": "https://raw.githubusercontent.com/mistval/kanji_images/master/gifs/9700.gif",
    "uri": "https://jisho.org/search/%E9%9C%80%23kanji"
  },
  "hanviet": [
    "nhu"
  ],
  "vietnameseMeaning": [
    "① Ðợi. Như tương nhu 相需 cùng đợi. ② Dùng. Như quân nhu 軍需 đồ dùng trong quân. ③ Lần lữa. Như sách Tả truyện 左傳 nói nhu sự chi tặc giã 需事之賊也 lần lữa là cái hại cho công việc vậy. (văn) Như 懦 (bộ 忄). (văn) Như 軟 (bộ 車). ①Nhu cầu, sự cần dùng, sự cần thiết: 按需分配 Phân phối theo nhu cầu; ② Cần: 他需款甚殷 Nó rất cần tiền; ③ (văn) Lần lữa, trì hoãn, do dự: 需，事之賊也 Lần lữa là cái hại cho công việc (Tả truyện); ④ (văn) Đợi: 相需 Đợi nhau."
  ],
  "jlpt": "1",
  "frequency": "935",
  "grade": "8"
}