{
  "id": "霸",
  "kanjialiveData": null,
  "jishoData": {
    "query": "霸",
    "found": true,
    "strokeCount": 21,
    "meaning": "supremacy, leadership",
    "kunyomi": [
      "はたがしら"
    ],
    "onyomi": [
      "ハ",
      "ハク"
    ],
    "onyomiExamples": [
      {
        "example": "那覇",
        "reading": "ナハ",
        "meaning": "Naha (city in Okinawa)"
      }
    ],
    "kunyomiExamples": [],
    "radical": {
      "symbol": "雨",
      "meaning": "rain"
    },
    "parts": [
      "月",
      "雨",
      "革"
    ],
    "strokeOrderDiagramUri": "http://classic.jisho.org/static/images/stroke_diagrams/38712_frames.png",
    "strokeOrderSvgUri": "https://d1w6u4xc3l95km.cloudfront.net/kanji-2015-03/09738.svg",
    "strokeOrderGifUri": "https://raw.githubusercontent.com/mistval/kanji_images/master/gifs/9738.gif",
    "uri": "https://jisho.org/search/%E9%9C%B8%23kanji"
  },
  "hanviet": [
    "bá"
  ],
  "vietnameseMeaning": [
    "① Chỗ chấm đen trong mặt trăng, bây giờ dùng chữ phách 魄. ② Một âm là bá. Làm trùm trưởng cả các nước chư hầu gọi là bá. Nguyễn Du 阮攸: Lưu thuỷ phù vân thất bá đồ 流水浮雲失霸圖 (Sở vọng 楚望) nước trôi mây nổi, sạch hết mưu đồ làm bá làm vua. ③ Tục gọi các kẻ cường hào là bá. Như bá chiếm 霸佔 ăn hiếp, lấy hiếp, ăn hiếp người chiếm riêng làm phần mình. Kẻ cường hào ăn hiếp dân gọi là ác bá 惡霸. ① Trùm (các nước chư hầu), bá chủ, minh chủ: 稱霸世界 Làm bá chủ thế giới; 此五霸之伐也！ Đó là công nghiệp hệt như ngũ bá! (Sử kí); 誠如是則霸業可成 Nếu thật như thế thì nghiệp bá có thể thành được (Gia Cát Lượng: Thảo lư đối); ② Cường hào, (ác) bá (kẻ ỷ cậy quyền thế bức hiếp dân chúng): 惡霸 Ác bá; ③ Chiếm đoạt, chiếm cứ, chiếm đóng. Mặt trăng (ánh trăng) thấy lần đầu trong tháng (dùng như 魄, bộ 鬼): 惟四月哉生霸 Chỉ tháng tư mới bắt đầu có ánh sáng trăng lần đầu trong tháng (Hán thư: Luật lịch chí, hạ) (哉 = 始)."
  ]
}