{
  "id": "韜",
  "kanjialiveData": null,
  "jishoData": {
    "query": "韜",
    "found": true,
    "strokeCount": 20,
    "meaning": "bag, wrapping",
    "kunyomi": [
      "ゆぶくろ",
      "ゆみぶくろ",
      "つつ.む"
    ],
    "onyomi": [
      "トウ"
    ],
    "onyomiExamples": [
      {
        "example": "韜晦",
        "reading": "トウカイ",
        "meaning": "concealing one's talents, status, intentions, etc., maintaining a strict incognito, self-effacement"
      },
      {
        "example": "韜晦趣味",
        "reading": "トウカイシュミ",
        "meaning": "propensity to efface oneself, being prone to conceal one's talent"
      },
      {
        "example": "天津鞴韜",
        "reading": "テンシンフクトウ",
        "meaning": "bellows (of the) imperial harbor, Shinto Buddhist doctrines"
      }
    ],
    "kunyomiExamples": [],
    "radical": {
      "symbol": "韋",
      "meaning": "tanned leather"
    },
    "parts": [
      "口",
      "爪",
      "臼",
      "韋"
    ],
    "strokeOrderDiagramUri": "http://classic.jisho.org/static/images/stroke_diagrams/38876_frames.png",
    "strokeOrderSvgUri": "https://d1w6u4xc3l95km.cloudfront.net/kanji-2015-03/097dc.svg",
    "strokeOrderGifUri": "https://raw.githubusercontent.com/mistval/kanji_images/master/gifs/97dc.gif",
    "uri": "https://jisho.org/search/%E9%9F%9C%23kanji"
  },
  "vietnameseMeaning": [
    "① Cái túi đựng gươm, đựng cung. ② Giấu kín, phàm sự gì giấu kín không lộ ra đều gọi là thao. Như thao hối 韜晦 có tài có trí mà giữ kín đáo không cho người ta biết mình. ③ Phép binh, phép binh của ông Thái Công 太公 gọi là lục thao 六韜. Người có tài tháo vát giỏi gọi là thao lược 韜畧, có tài làm tướng dùng binh giỏi cũng gọi là thao lược. Cũng có khi viết thao 弢. (văn) ① Vỏ (bao) kiếm (hoặc cung); ② Phép dùng binh, chiến thuật, thao lược; ③ Giấu.【韜光養晦】thao quang dưỡng hối Giấu tài; ④ Ăn không ngồi rồi."
  ],
  "hanviet": [
    "thao"
  ]
}